kt_osc/__init__.py
kt_osc/cli.py
kt_osc/kt_osc.py
kt_osc-0.2.1.dist-info/entry_points.txt
kt_osc-0.2.1.dist-info/LICENSE
kt_osc-0.2.1.dist-info/WHEEL
kt_osc-0.2.1.dist-info/METADATA
kt_osc-0.2.1.dist-info/RECORD
